jouissance/__init__.py
jouissance/pt/__init__.py
jouissance/pt/arch.py
jouissance/pt/data.py
jouissance/test/pt_arch_test.py
jouissance/test/pt_data_test.py
jouissance/test/tf_arch_test.py
jouissance/test/tf_data_test.py
jouissance/test/tf_runs_test.py
jouissance/test/util_conf_test.py
jouissance/test/util_file_test.py
jouissance/tf/__init__.py
jouissance/tf/arch.py
jouissance/tf/data.py
jouissance/tf/loss.py
jouissance/tf/runs.py
jouissance/tf/wgan.py
jouissance/util/__init__.py
jouissance/util/_configs.yaml
jouissance/util/conf.py
jouissance/util/file.py
jouissance-0.2.2.dist-info/WHEEL
jouissance-0.2.2.dist-info/METADATA
jouissance-0.2.2.dist-info/RECORD
