Metadata-Version: 2.1
Name: jouissance
Version: 0.2.2
Summary: jouissance
Keywords: jouissance
Author-email: ngam <ezngam@gmail.com>
Requires-Python: >=3.7
Classifier: Programming Language :: Python :: 3
Classifier: Programming Language :: Python :: 3 :: Only
Classifier: License :: OSI Approved :: MIT License
Classifier: Intended Audience :: Science/Research
Classifier: Topic :: Scientific/Engineering
Requires-Dist: jouissance[test] ; extra == "dev"
Requires-Dist: autopep8 ; extra == "dev"
Requires-Dist: typing ; extra == "dev"
Requires-Dist: build ; extra == "dev"
Requires-Dist: jupyter-book ; extra == "dev"
Requires-Dist: ghp-import ; extra == "dev"
Requires-Dist: jupyterlab ; extra == "dev"
Requires-Dist: matplotlib ; extra == "dev"
Requires-Dist: numba ; extra == "dev"
Requires-Dist: pandas ; extra == "dev"
Requires-Dist: sympy ; extra == "dev"
Requires-Dist: scipy ; extra == "dev"
Requires-Dist: numpy ; extra == "dev"
Requires-Dist: jax ; extra == "dev"
Requires-Dist: jaxlib ; extra == "dev"
Requires-Dist: keras-cv ; extra == "dev"
Requires-Dist: xarray ; extra == "dev"
Requires-Dist: pylint ; extra == "test"
Requires-Dist: pytype ; extra == "test"
Requires-Dist: flake8 ; extra == "test"
Requires-Dist: pytest ; extra == "test"
Requires-Dist: h5py ; extra == "test"
Requires-Dist: netCDF4 ; extra == "test"
Requires-Dist: fsspec ; extra == "test"
Requires-Dist: gcsfs ; extra == "test"
Requires-Dist: s3fs ; extra == "test"
Requires-Dist: adlfs ; extra == "test"
Requires-Dist: pyyaml ; extra == "test"
Requires-Dist: tensorflow ; extra == "test"
Requires-Dist: torch ; extra == "test"
Requires-Dist: torchvision ; extra == "test"
Project-URL: homepage, https://github.com/ngam/jouissance
Project-URL: repository, https://github.com/ngam/jouissance
Provides-Extra: dev
Provides-Extra: test
